idscrub/__init__.py
idscrub/locations.py
idscrub/scrub.py
idscrub-1.1.2.dist-info/licenses/LICENSE
notebooks/basic_usage.ipynb
test/conftest.py
test/test_all.py
test/test_chain.py
test/test_dataframe.py
test/test_huggingface.py
test/test_id.py
test/test_label.py
test/test_log.py
test/test_phonenumbers.py
test/test_presidio.py
test/test_regex.py
test/test_scrub.py
test/test_spacy.py
idscrub-1.1.2.dist-info/METADATA
idscrub-1.1.2.dist-info/WHEEL
idscrub-1.1.2.dist-info/top_level.txt
idscrub-1.1.2.dist-info/RECORD
