Metadata-Version: 2.4
Name: idscrub
Version: 1.1.2
Author: Department for Business and Trade
Classifier: Development Status :: 3 - Alpha
Requires-Python: >=3.12
License-File: LICENSE
Requires-Dist: ipykernel>=7.1.0
Requires-Dist: ipywidgets
Requires-Dist: numpy>=2.3.4
Requires-Dist: pandas<3.0
Requires-Dist: phonenumbers>=9.0.18
Requires-Dist: pip>=25.3
Requires-Dist: spacy-transformers>=1.3.9
Requires-Dist: tqdm>=4.67.1
Requires-Dist: presidio-analyzer
Requires-Dist: presidio-anonymizer
Provides-Extra: trf
Requires-Dist: en_core_web_trf; extra == "trf"
Dynamic: license-file
